__init__.py
pyproject.toml
tdb/__main__.py
tdb/addon.py
tdb/cli.py
tdb/config.py
tdb/db.py
tdb/html.js
tdb/html.py
tdb/rake.py
tdb/records.py
tdb/server.py
tdb/session.py
tdb/style.css
tdb/tags.py
pypi_tdb-0.0.6.dist-info/METADATA
pypi_tdb-0.0.6.dist-info/WHEEL
pypi_tdb-0.0.6.dist-info/licenses/LICENSE
pypi_tdb-0.0.6.dist-info/RECORD
