Metadata-Version: 2.3
Name: pypi-tdb
Version: 0.0.6
Summary: tdb: text based database with tagging
Project-URL: Homepage, https://github.com/graehu/tdb
Project-URL: Bug Tracker, https://github.com/graehu/tdb/issues
Author-email: Graham Hughes <graehu@gmail.com>
License-File: LICENSE
Classifier: License :: OSI Approved :: MIT License
Classifier: Operating System :: OS Independent
Classifier: Programming Language :: Python :: 3
Requires-Python: >=3.11
